my_ml_package/__init__.py
my_ml_package/models/__init__.py
my_ml_package/models/decision_tree.py
my_ml_package/models/knn.py
my_ml_package/models/linear_regression.py
my_ml_package/models/logistic_regression.py
my_ml_package/models/multivariate_regression.py
my_ml_package/models/random_forest.py
my_ml_package/utils/__init__.py
my_ml_package/utils/data_processing.py
my_ml_package/utils/evaluation.py
Vishnupriya_ml_package-0.1.0.dist-info/METADATA
Vishnupriya_ml_package-0.1.0.dist-info/WHEEL
Vishnupriya_ml_package-0.1.0.dist-info/entry_points.txt
Vishnupriya_ml_package-0.1.0.dist-info/top_level.txt
Vishnupriya_ml_package-0.1.0.dist-info/RECORD
